faust_avro_model_codegen/__init__.py
faust_avro_model_codegen/__main__.py
faust_avro_model_codegen/models_generator.py
faust_avro_model_codegen/schema_dir_parser.py
faust_avro_model_codegen/schema_verifier.py
faust_avro_model_codegen/settings.py
faust_avro_model_codegen/template_renderer.py
faust_avro_model_codegen/template_writer.py
faust_avro_model_codegen/templates/enum.py.jinja2
faust_avro_model_codegen/templates/faust_record.jinja2
faust_avro_model_codegen/templates/models.py.jinja2
faust_avro_model_codegen/types.py
faust_avro_model_codegen-0.1.8.dist-info/LICENSE
faust_avro_model_codegen-0.1.8.dist-info/METADATA
faust_avro_model_codegen-0.1.8.dist-info/WHEEL
faust_avro_model_codegen-0.1.8.dist-info/RECORD
