Metadata-Version: 2.1
Name: faust-avro-model-codegen
Version: 0.1.8
Summary: Generate Faust Avro Models from Avro Schema files.
Home-page: https://github.com/bboggs-streambit/faust-avro-model-codegen
License: MIT
Author: Sean Zicari
Author-email: szicari@streambit.software, Brad Boggs <bboggs@streambit.software
Requires-Python: >=3.10
Classifier: License :: OSI Approved :: MIT License
Classifier: Programming Language :: Python :: 3
Classifier: Programming Language :: Python :: 3.10
Classifier: Programming Language :: Python :: 3.11
Requires-Dist: autoflake (>2.0.0)
Requires-Dist: black (>23.0.0)
Requires-Dist: dataclasses-avroschema[faust] (>=0.58.0)
Requires-Dist: httpx (>=0.24.0)
Requires-Dist: isort (>=5.13.2,<6.0.0)
Requires-Dist: jinja2 (>=3.1.3,<4.0.0)
Requires-Dist: mode-streaming (<0.4.0)
Requires-Dist: plumbum (>=1.8.2,<2.0.0)
Requires-Dist: pydantic (>1.0.0)
Requires-Dist: rich (>=13.7.1,<14.0.0)
Requires-Dist: tomlkit (>=0.12.0)
Requires-Dist: typer (>=0.9.0)
Project-URL: Repository, https://github.com/bboggs-streambit/faust-avro-model-codegen
